aivoice_2/__init__.py
MultilingualSpeaker-0.0.1.dist-info/METADATA
MultilingualSpeaker-0.0.1.dist-info/WHEEL
MultilingualSpeaker-0.0.1.dist-info/top_level.txt
MultilingualSpeaker-0.0.1.dist-info/RECORD
