Metadata-Version: 2.1
Name: MultilingualSpeaker
Version: 0.0.1
Summary: A brief description of the library
Home-page: https://github.com/NPO_KS903/MultilingualSpeaker
Author: NPO_KS_903
Author-email: xksxkatuyoshi0009@gmail.com
Classifier: Programming Language :: Python :: 3
Classifier: License :: OSI Approved :: MIT License
Classifier: Operating System :: OS Independent
Requires-Python: >=3.6
Requires-Dist: deep-translator
Requires-Dist: pyttsx3
